langcache/__init__.py
langcache/_hooks/__init__.py
langcache/_hooks/registration.py
langcache/_hooks/sdkhooks.py
langcache/_hooks/types.py
langcache/_version.py
langcache/basesdk.py
langcache/errors/__init__.py
langcache/errors/apierror.py
langcache/errors/authenticationerrorresponsecontent.py
langcache/errors/badrequesterrorresponsecontent.py
langcache/errors/forbiddenerrorresponsecontent.py
langcache/errors/langcacheerror.py
langcache/errors/no_response_error.py
langcache/errors/notfounderrorresponsecontent.py
langcache/errors/payloadtoolargeerrorresponsecontent.py
langcache/errors/resourceunavailableerrorresponsecontent.py
langcache/errors/responsevalidationerror.py
langcache/errors/toomanyrequestserrorresponsecontent.py
langcache/errors/unexpectederrorresponsecontent.py
langcache/httpclient.py
langcache/models/__init__.py
langcache/models/authenticationerroruri.py
langcache/models/badrequesterroruri.py
langcache/models/cacheentry.py
langcache/models/deletebyidop.py
langcache/models/deletequeryop.py
langcache/models/deletequeryrequest.py
langcache/models/deletequeryresponse.py
langcache/models/fielderror.py
langcache/models/flushop.py
langcache/models/forbiddenerroruri.py
langcache/models/internal/__init__.py
langcache/models/internal/globals.py
langcache/models/notfounderroruri.py
langcache/models/payloadtoolargeerroruri.py
langcache/models/resourceunavailableerroruri.py
langcache/models/searchop.py
langcache/models/searchrequest.py
langcache/models/searchresponse.py
langcache/models/searchstrategy.py
langcache/models/security.py
langcache/models/setop.py
langcache/models/setrequest.py
langcache/models/setresponse.py
langcache/models/toomanyrequestserroruri.py
langcache/models/unexpectederroruri.py
langcache/py.typed
langcache/sdk.py
langcache/sdkconfiguration.py
langcache/types/__init__.py
langcache/types/basemodel.py
langcache/utils/__init__.py
langcache/utils/annotations.py
langcache/utils/datetimes.py
langcache/utils/enums.py
langcache-0.11.0.dist-info/METADATA
langcache-0.11.0.dist-info/WHEEL
langcache-0.11.0.dist-info/RECORD
